{
  "Sources/GryphonLib/ArrayReference.swift": {
    "ast-dump": "Bootstrap/ArrayReference.swiftASTDump",
  },
  "Sources/GryphonLib/CwlRandom.swift": {
    "ast-dump": "Bootstrap/CwlRandom.swiftASTDump",
  },
  "Sources/GryphonLib/GRYAST.swift": {
    "ast-dump": "Bootstrap/GRYAST.swiftASTDump",
  },
  "Sources/GryphonLib/GRYCodable.swift": {
    "ast-dump": "Bootstrap/GRYCodable.swiftASTDump",
  },
  "Sources/GryphonLib/GRYCompiler.swift": {
    "ast-dump": "Bootstrap/GRYCompiler.swiftASTDump",
  },
  "Sources/GryphonLib/GRYExtensions.swift": {
    "ast-dump": "Bootstrap/GRYExtensions.swiftASTDump",
  },
  "Sources/GryphonLib/GRYKotlinTranslator.swift": {
    "ast-dump": "Bootstrap/GRYKotlinTranslator.swiftASTDump",
  },
  "Sources/GryphonLib/GRYLibraryTranspilationPass.swift": {
    "ast-dump": "Bootstrap/GRYLibraryTranspilationPass.swiftASTDump",
  },
  "Sources/GryphonLib/GRYPrintableAsTree.swift": {
    "ast-dump": "Bootstrap/GRYPrintableAsTree.swiftASTDump",
  },
  "Sources/GryphonLib/GRYShell.swift": {
    "ast-dump": "Bootstrap/GRYShell.swiftASTDump",
  },
  "Sources/GryphonLib/GRYSwift4Translator.swift": {
    "ast-dump": "Bootstrap/GRYSwift4Translator.swiftASTDump",
  },
  "Sources/GryphonLib/GRYSwift5Translator.swift": {
    "ast-dump": "Bootstrap/GRYSwift5Translator.swiftASTDump",
  },
  "Sources/GryphonLib/GRYSwiftAst.swift": {
    "ast-dump": "Bootstrap/GRYSwiftAst.swiftASTDump",
  },
  "Sources/GryphonLib/GRYTranspilationPass.swift": {
    "ast-dump": "Bootstrap/GRYTranspilationPass.swiftASTDump",
  },
  "Sources/GryphonLib/GRYUtils.swift": {
    "ast-dump": "Bootstrap/GRYUtils.swiftASTDump",
  },
}
